Workbook

Sheet Employee_Master
A1: Employee_ID | B1: Employee_Name | C1: Department | D1: Role | E1: Hourly_Base_Rate | F1: Standard_Hours_Per_Day
A2: EMP-101 | B2: Sarah Jenkins | C2: Operations | D2: Shift Lead | E2: 32.5 | F2: 8
A3: EMP-102 | B3: Marcus Chen | C3: Logistics | D3: Coordinator | E3: 24 | F3: 8
A4: EMP-103 | B4: Elena Rostova | C4: Warehouse | D4: Specialist | E4: 21 | F4: 8
A5: EMP-104 | B5: David Miller | C5: Operations | D5: Senior Analyst | E5: 38 | F5: 8
A6: EMP-105 | B6: Priya Sharma | C6: Logistics | D6: Inventory Tech | E6: 22.5 | F6: 8
A7: EMP-106 | B7: James Wilson | C7: Warehouse | D7: Loader | E7: 19.5 | F7: 8

Sheet Shift_Log_Engine
A1: Log_ID | B1: Date | C1: Employee_ID | D1: Scheduled_Hours | E1: Actual_Hours | F1: Absent_Flag | G1: Regular_Hours | H1: Overtime_Hours | I1: Absence_Impact
A2: LOG-1001 | B2: 46296 | C2: EMP-101 | D2: 8 | E2: 10 | F2: No | G2: =IF(F2="Yes", 0, MIN(D2, E2)) -> 8 | H2: =IF(F2="Yes", 0, MAX(0, E2 - D2)) -> 2 | I2: =IF(F2="Yes", 1, 0) -> 0
A3: LOG-1002 | B3: 46296 | C3: EMP-102 | D3: 8 | E3: 8 | F3: No | G3: =IF(F3="Yes", 0, MIN(D3, E3)) -> 8 | H3: =IF(F3="Yes", 0, MAX(0, E3 - D3)) -> 0 | I3: =IF(F3="Yes", 1, 0) -> 0
A4: LOG-1003 | B4: 46296 | C4: EMP-103 | D4: 8 | E4: 0 | F4: Yes | G4: =IF(F4="Yes", 0, MIN(D4, E4)) -> 0 | H4: =IF(F4="Yes", 0, MAX(0, E4 - D4)) -> 0 | I4: =IF(F4="Yes", 1, 0) -> 1
A5: LOG-1004 | B5: 46297 | C5: EMP-104 | D5: 8 | E5: 9.5 | F5: No | G5: =IF(F5="Yes", 0, MIN(D5, E5)) -> 8 | H5: =IF(F5="Yes", 0, MAX(0, E5 - D5)) -> 1.5 | I5: =IF(F5="Yes", 1, 0) -> 0
A6: LOG-1005 | B6: 46297 | C6: EMP-105 | D6: 8 | E6: 11 | F6: No | G6: =IF(F6="Yes", 0, MIN(D6, E6)) -> 8 | H6: =IF(F6="Yes", 0, MAX(0, E6 - D6)) -> 3 | I6: =IF(F6="Yes", 1, 0) -> 0
A7: LOG-1006 | B7: 46297 | C7: EMP-106 | D7: 8 | E7: 8 | F7: No | G7: =IF(F7="Yes", 0, MIN(D7, E7)) -> 8 | H7: =IF(F7="Yes", 0, MAX(0, E7 - D7)) -> 0 | I7: =IF(F7="Yes", 1, 0) -> 0

Sheet Labor_Cost_Forecaster
A1: Employee_ID | B1: Employee_Name | C1: Department | D1: Hourly_Base_Rate | E1: Total_Regular_Hours | F1: Total_OT_Hours | G1: Regular_Payroll_Cost | H1: Overtime_Payroll_Cost | I1: Total_Payroll_Liability
A2: EMP-101 | B2: =_xlfn.XLOOKUP(A2, Employee_Master!$A$2:$A$7, Employee_Master!$B$2:$B$7, "Unknown") -> Sarah Jenkins | C2: =_xlfn.XLOOKUP(A2, Employee_Master!$A$2:$A$7, Employee_Master!$C$2:$C$7, "N/A") -> Operations | D2: =_xlfn.XLOOKUP(A2, Employee_Master!$A$2:$A$7, Employee_Master!$E$2:$E$7, 0) -> 32.5 | E2: =SUMIF(Shift_Log_Engine!$C$2:$C$50, A2, Shift_Log_Engine!$G$2:$G$50) -> 8 | F2: =SUMIF(Shift_Log_Engine!$C$2:$C$50, A2, Shift_Log_Engine!$H$2:$H$50) -> 2 | G2: =E2 * D2 -> 260 | H2: =F2 * D2 * 1.5 -> 97.5 | I2: =G2 + H2 -> 357.5
A3: EMP-102 | B3: =_xlfn.XLOOKUP(A3, Employee_Master!$A$2:$A$7, Employee_Master!$B$2:$B$7, "Unknown") -> Marcus Chen | C3: =_xlfn.XLOOKUP(A3, Employee_Master!$A$2:$A$7, Employee_Master!$C$2:$C$7, "N/A") -> Logistics | D3: =_xlfn.XLOOKUP(A3, Employee_Master!$A$2:$A$7, Employee_Master!$E$2:$E$7, 0) -> 24 | E3: =SUMIF(Shift_Log_Engine!$C$2:$C$50, A3, Shift_Log_Engine!$G$2:$G$50) -> 8 | F3: =SUMIF(Shift_Log_Engine!$C$2:$C$50, A3, Shift_Log_Engine!$H$2:$H$50) -> 0 | G3: =E3 * D3 -> 192 | H3: =F3 * D3 * 1.5 -> 0 | I3: =G3 + H3 -> 192
A4: EMP-103 | B4: =_xlfn.XLOOKUP(A4, Employee_Master!$A$2:$A$7, Employee_Master!$B$2:$B$7, "Unknown") -> Elena Rostova | C4: =_xlfn.XLOOKUP(A4, Employee_Master!$A$2:$A$7, Employee_Master!$C$2:$C$7, "N/A") -> Warehouse | D4: =_xlfn.XLOOKUP(A4, Employee_Master!$A$2:$A$7, Employee_Master!$E$2:$E$7, 0) -> 21 | E4: =SUMIF(Shift_Log_Engine!$C$2:$C$50, A4, Shift_Log_Engine!$G$2:$G$50) -> 0 | F4: =SUMIF(Shift_Log_Engine!$C$2:$C$50, A4, Shift_Log_Engine!$H$2:$H$50) -> 0 | G4: =E4 * D4 -> 0 | H4: =F4 * D4 * 1.5 -> 0 | I4: =G4 + H4 -> 0
A5: EMP-104 | B5: =_xlfn.XLOOKUP(A5, Employee_Master!$A$2:$A$7, Employee_Master!$B$2:$B$7, "Unknown") -> David Miller | C5: =_xlfn.XLOOKUP(A5, Employee_Master!$A$2:$A$7, Employee_Master!$C$2:$C$7, "N/A") -> Operations | D5: =_xlfn.XLOOKUP(A5, Employee_Master!$A$2:$A$7, Employee_Master!$E$2:$E$7, 0) -> 38 | E5: =SUMIF(Shift_Log_Engine!$C$2:$C$50, A5, Shift_Log_Engine!$G$2:$G$50) -> 8 | F5: =SUMIF(Shift_Log_Engine!$C$2:$C$50, A5, Shift_Log_Engine!$H$2:$H$50) -> 1.5 | G5: =E5 * D5 -> 304 | H5: =F5 * D5 * 1.5 -> 85.5 | I5: =G5 + H5 -> 389.5
A6: EMP-105 | B6: =_xlfn.XLOOKUP(A6, Employee_Master!$A$2:$A$7, Employee_Master!$B$2:$B$7, "Unknown") -> Priya Sharma | C6: =_xlfn.XLOOKUP(A6, Employee_Master!$A$2:$A$7, Employee_Master!$C$2:$C$7, "N/A") -> Logistics | D6: =_xlfn.XLOOKUP(A6, Employee_Master!$A$2:$A$7, Employee_Master!$E$2:$E$7, 0) -> 22.5 | E6: =SUMIF(Shift_Log_Engine!$C$2:$C$50, A6, Shift_Log_Engine!$G$2:$G$50) -> 8 | F6: =SUMIF(Shift_Log_Engine!$C$2:$C$50, A6, Shift_Log_Engine!$H$2:$H$50) -> 3 | G6: =E6 * D6 -> 180 | H6: =F6 * D6 * 1.5 -> 101.25 | I6: =G6 + H6 -> 281.25
A7: EMP-106 | B7: =_xlfn.XLOOKUP(A7, Employee_Master!$A$2:$A$7, Employee_Master!$B$2:$B$7, "Unknown") -> James Wilson | C7: =_xlfn.XLOOKUP(A7, Employee_Master!$A$2:$A$7, Employee_Master!$C$2:$C$7, "N/A") -> Warehouse | D7: =_xlfn.XLOOKUP(A7, Employee_Master!$A$2:$A$7, Employee_Master!$E$2:$E$7, 0) -> 19.5 | E7: =SUMIF(Shift_Log_Engine!$C$2:$C$50, A7, Shift_Log_Engine!$G$2:$G$50) -> 8 | F7: =SUMIF(Shift_Log_Engine!$C$2:$C$50, A7, Shift_Log_Engine!$H$2:$H$50) -> 0 | G7: =E7 * D7 -> 156 | H7: =F7 * D7 * 1.5 -> 0 | I7: =G7 + H7 -> 156
A8: TOTAL | D8: =SUM(D2:D7) -> 157.5 | E8: =SUM(E2:E7) -> 40 | F8: =SUM(F2:F7) -> 6.5 | G8: =SUM(G2:G7) -> 1092 | H8: =SUM(H2:H7) -> 284.25 | I8: =SUM(I2:I7) -> 1376.25

Sheet Workforce_Analytics_Dashboard
A1: EXECUTIVE WORKFORCE CAPACITY & LABOR COST DASHBOARD
A2: Total Payroll Expenditure | C2: Overtime Leakage Ratio | E2: Workforce Utilization Rate
A3: =SUM(Labor_Cost_Forecaster!I2:I7) -> 1376.25 | C3: =SUM(Labor_Cost_Forecaster!H2:H7) / SUM(Labor_Cost_Forecaster!I2:I7) -> 0.20653951 | E3: =SUM(Shift_Log_Engine!E2:E50) / SUM(Shift_Log_Engine!D2:D50) -> 0.96875
A6: Department | B6: Regular Cost | C6: Overtime Cost | D6: Total Cost
A7: Operations | B7: =SUMIF(Labor_Cost_Forecaster!$C$2:$C$7, A7, Labor_Cost_Forecaster!$G$2:$G$7) -> 564 | C7: =SUMIF(Labor_Cost_Forecaster!$C$2:$C$7, A7, Labor_Cost_Forecaster!$H$2:$H$7) -> 183 | D7: =B7 + C7 -> 747
A8: Logistics | B8: =SUMIF(Labor_Cost_Forecaster!$C$2:$C$7, A8, Labor_Cost_Forecaster!$G$2:$G$7) -> 372 | C8: =SUMIF(Labor_Cost_Forecaster!$C$2:$C$7, A8, Labor_Cost_Forecaster!$H$2:$H$7) -> 101.25 | D8: =B8 + C8 -> 473.25
A9: Warehouse | B9: =SUMIF(Labor_Cost_Forecaster!$C$2:$C$7, A9, Labor_Cost_Forecaster!$G$2:$G$7) -> 156 | C9: =SUMIF(Labor_Cost_Forecaster!$C$2:$C$7, A9, Labor_Cost_Forecaster!$H$2:$H$7) -> 0 | D9: =B9 + C9 -> 156
